django_choice/__init__.py
django_choice/choices.py
django_choice-1.0.3.dist-info/DESCRIPTION.rst
django_choice-1.0.3.dist-info/LICENSE.txt
django_choice-1.0.3.dist-info/METADATA
django_choice-1.0.3.dist-info/RECORD
django_choice-1.0.3.dist-info/WHEEL
django_choice-1.0.3.dist-info/metadata.json
django_choice-1.0.3.dist-info/top_level.txt
