Metadata-Version: 2.0
Name: django-choice
Version: 1.0.3
Summary: Choices made simple for Django model and form fields
Home-page: https://github.com/denhartog/django-choice/
Author: UNKNOWN
Author-email: UNKNOWN
License: UNKNOWN
Platform: UNKNOWN
Classifier: Framework :: Django
Classifier: Programming Language :: Python
